deepgoplus/__init__.py
deepgoplus/aminoacids.py
deepgoplus/main.py
deepgoplus/utils.py
deepgoplus-1.0.2.dist-info/LICENSE
deepgoplus-1.0.2.dist-info/METADATA
deepgoplus-1.0.2.dist-info/WHEEL
deepgoplus-1.0.2.dist-info/entry_points.txt
deepgoplus-1.0.2.dist-info/top_level.txt
deepgoplus-1.0.2.dist-info/zip-safe
deepgoplus-1.0.2.dist-info/RECORD
