Metadata-Version: 2.1
Name: deepgoplus
Version: 1.0.2
Summary: DeepGOPlus function predictor
Download-URL: https://github.com/bio-ontology-research-group/deepgoplus/archive/v1.0.2.tar.gz
Author: Maxat Kulmanov
Author-email: maxat.kulmanov@kaust.edu.sa
License: Apache 2.0
Requires-Python: >=3.7, <3.8
License-File: LICENSE
Requires-Dist: click <8
Requires-Dist: scikit-learn
Requires-Dist: pandas
Requires-Dist: tensorflow <2.4
Requires-Dist: numpy <2.0
Requires-Dist: scipy
